jack_server/__init__.py
jack_server/_driver.py
jack_server/_jslist.py
jack_server/_lib.py
jack_server/_output.py
jack_server/_parameter.py
jack_server/_server.py
jack_server/py.typed
jack_server-0.2.0.dist-info/LICENSE
jack_server-0.2.0.dist-info/METADATA
jack_server-0.2.0.dist-info/WHEEL
jack_server-0.2.0.dist-info/RECORD
