Metadata-Version: 2.1
Name: jack-server
Version: 0.2.0
Summary: Control JACK server with Python
License: MIT
Author: Lev Vereshchagin
Author-email: mail@vrslev.com
Requires-Python: >=3.8,<4.0
Classifier: License :: OSI Approved :: MIT License
Classifier: Programming Language :: Python :: 3
Classifier: Programming Language :: Python :: 3.8
Classifier: Programming Language :: Python :: 3.9
Classifier: Programming Language :: Python :: 3.10
Classifier: Programming Language :: Python :: 3.11
Classifier: Programming Language :: Python :: 3.12
